{"nodes": [{"id": "c_projects_arza_ecommerce_api_controllers_cartcontroller_cs", "label": "CartController.cs", "file_type": "code", "source_file": "C:\\Projects\\Arza\\ECommerce.API\\Controllers\\CartController.cs", "source_location": "L1"}, {"id": "controllers_cartcontroller_cartcontroller", "label": "CartController", "file_type": "code", "source_file": "C:\\Projects\\Arza\\ECommerce.API\\Controllers\\CartController.cs", "source_location": "L11"}, {"id": "controllerbase", "label": "ControllerBase", "file_type": "code", "source_file": "", "source_location": ""}, {"id": "icartservice", "label": "ICartService", "file_type": "code", "source_file": "C:\\Projects\\Arza\\ECommerce.API\\Controllers\\CartController.cs", "source_location": "L15"}, {"id": "ilogger", "label": "ILogger", "file_type": "code", "source_file": "C:\\Projects\\Arza\\ECommerce.API\\Controllers\\CartController.cs", "source_location": "L16"}, {"id": "imemorycache", "label": "IMemoryCache", "file_type": "code", "source_file": "C:\\Projects\\Arza\\ECommerce.API\\Controllers\\CartController.cs", "source_location": "L17"}, {"id": "controllers_cartcontroller_cartcontroller_getuserid", "label": ".GetUserId()", "file_type": "code", "source_file": "C:\\Projects\\Arza\\ECommerce.API\\Controllers\\CartController.cs", "source_location": "L26"}, {"id": "controllers_cartcontroller_cartcontroller_getsessionid", "label": ".GetSessionId()", "file_type": "code", "source_file": "C:\\Projects\\Arza\\ECommerce.API\\Controllers\\CartController.cs", "source_location": "L28"}, {"id": "controllers_cartcontroller_cartcontroller_getcachekey", "label": ".GetCacheKey()", "file_type": "code", "source_file": "C:\\Projects\\Arza\\ECommerce.API\\Controllers\\CartController.cs", "source_location": "L42"}, {"id": "controllers_cartcontroller_cartcontroller_getcart", "label": ".GetCart()", "file_type": "code", "source_file": "C:\\Projects\\Arza\\ECommerce.API\\Controllers\\CartController.cs", "source_location": "L53"}, {"id": "task", "label": "Task", "file_type": "code", "source_file": "C:\\Projects\\Arza\\ECommerce.API\\Controllers\\CartController.cs", "source_location": "L53"}, {"id": "actionresult", "label": "ActionResult", "file_type": "code", "source_file": "C:\\Projects\\Arza\\ECommerce.API\\Controllers\\CartController.cs", "source_location": "L53"}, {"id": "cartdto", "label": "CartDto", "file_type": "code", "source_file": "C:\\Projects\\Arza\\ECommerce.API\\Controllers\\CartController.cs", "source_location": "L53"}, {"id": "httpget", "label": "HttpGet", "file_type": "code", "source_file": "C:\\Projects\\Arza\\ECommerce.API\\Controllers\\CartController.cs", "source_location": "L53"}, {"id": "responsecache", "label": "ResponseCache", "file_type": "code", "source_file": "C:\\Projects\\Arza\\ECommerce.API\\Controllers\\CartController.cs", "source_location": "L53"}, {"id": "controllers_cartcontroller_cartcontroller_additem", "label": ".AddItem()", "file_type": "code", "source_file": "C:\\Projects\\Arza\\ECommerce.API\\Controllers\\CartController.cs", "source_location": "L73"}, {"id": "addtocartdto", "label": "AddToCartDto", "file_type": "code", "source_file": "C:\\Projects\\Arza\\ECommerce.API\\Controllers\\CartController.cs", "source_location": "L73"}, {"id": "httppost", "label": "HttpPost", "file_type": "code", "source_file": "C:\\Projects\\Arza\\ECommerce.API\\Controllers\\CartController.cs", "source_location": "L73"}, {"id": "controllers_cartcontroller_cartcontroller_updateitem", "label": ".UpdateItem()", "file_type": "code", "source_file": "C:\\Projects\\Arza\\ECommerce.API\\Controllers\\CartController.cs", "source_location": "L94"}, {"id": "updatecartitemdto", "label": "UpdateCartItemDto", "file_type": "code", "source_file": "C:\\Projects\\Arza\\ECommerce.API\\Controllers\\CartController.cs", "source_location": "L94"}, {"id": "controllers_cartcontroller_cartcontroller_removeitem", "label": ".RemoveItem()", "file_type": "code", "source_file": "C:\\Projects\\Arza\\ECommerce.API\\Controllers\\CartController.cs", "source_location": "L119"}, {"id": "httpdelete", "label": "HttpDelete", "file_type": "code", "source_file": "C:\\Projects\\Arza\\ECommerce.API\\Controllers\\CartController.cs", "source_location": "L119"}, {"id": "controllers_cartcontroller_cartcontroller_clearcart", "label": ".ClearCart()", "file_type": "code", "source_file": "C:\\Projects\\Arza\\ECommerce.API\\Controllers\\CartController.cs", "source_location": "L135"}, {"id": "controllers_cartcontroller_cartcontroller_mergeguestcart", "label": ".MergeGuestCart()", "file_type": "code", "source_file": "C:\\Projects\\Arza\\ECommerce.API\\Controllers\\CartController.cs", "source_location": "L146"}], "edges": [{"source": "c_projects_arza_ecommerce_api_controllers_cartcontroller_cs", "target": "mvc", "relation": "imports", "context": "import", "confidence": "EXTRACTED", "source_file": "C:\\Projects\\Arza\\ECommerce.API\\Controllers\\CartController.cs", "source_location": "L1", "weight": 1.0}, {"source": "c_projects_arza_ecommerce_api_controllers_cartcontroller_cs", "target": "dtos", "relation": "imports", "context": "import", "confidence": "EXTRACTED", "source_file": "C:\\Projects\\Arza\\ECommerce.API\\Controllers\\CartController.cs", "source_location": "L2", "weight": 1.0}, {"source": "c_projects_arza_ecommerce_api_controllers_cartcontroller_cs", "target": "interfaces", "relation": "imports", "context": "import", "confidence": "EXTRACTED", "source_file": "C:\\Projects\\Arza\\ECommerce.API\\Controllers\\CartController.cs", "source_location": "L3", "weight": 1.0}, {"source": "c_projects_arza_ecommerce_api_controllers_cartcontroller_cs", "target": "claims", "relation": "imports", "context": "import", "confidence": "EXTRACTED", "source_file": "C:\\Projects\\Arza\\ECommerce.API\\Controllers\\CartController.cs", "source_location": "L4", "weight": 1.0}, {"source": "c_projects_arza_ecommerce_api_controllers_cartcontroller_cs", "target": "authorization", "relation": "imports", "context": "import", "confidence": "EXTRACTED", "source_file": "C:\\Projects\\Arza\\ECommerce.API\\Controllers\\CartController.cs", "source_location": "L5", "weight": 1.0}, {"source": "c_projects_arza_ecommerce_api_controllers_cartcontroller_cs", "target": "memory", "relation": "imports", "context": "import", "confidence": "EXTRACTED", "source_file": "C:\\Projects\\Arza\\ECommerce.API\\Controllers\\CartController.cs", "source_location": "L6", "weight": 1.0}, {"source": "c_projects_arza_ecommerce_api_controllers_cartcontroller_cs", "target": "appconstants", "relation": "imports", "context": "import", "confidence": "EXTRACTED", "source_file": "C:\\Projects\\Arza\\ECommerce.API\\Controllers\\CartController.cs", "source_location": "L7", "weight": 1.0}, {"source": "c_projects_arza_ecommerce_api_controllers_cartcontroller_cs", "target": "controllers_cartcontroller_cartcontroller", "relation": "contains", "confidence": "EXTRACTED", "source_file": "C:\\Projects\\Arza\\ECommerce.API\\Controllers\\CartController.cs", "source_location": "L11", "weight": 1.0}, {"source": "controllers_cartcontroller_cartcontroller", "target": "controllerbase", "relation": "inherits", "confidence": "EXTRACTED", "source_file": "C:\\Projects\\Arza\\ECommerce.API\\Controllers\\CartController.cs", "source_location": "L11", "weight": 1.0}, {"source": "controllers_cartcontroller_cartcontroller", "target": "icartservice", "relation": "references", "confidence": "EXTRACTED", "source_file": "C:\\Projects\\Arza\\ECommerce.API\\Controllers\\CartController.cs", "source_location": "L15", "weight": 1.0, "context": "field"}, {"source": "controllers_cartcontroller_cartcontroller", "target": "ilogger", "relation": "references", "confidence": "EXTRACTED", "source_file": "C:\\Projects\\Arza\\ECommerce.API\\Controllers\\CartController.cs", "source_location": "L16", "weight": 1.0, "context": "field"}, {"source": "controllers_cartcontroller_cartcontroller", "target": "imemorycache", "relation": "references", "confidence": "EXTRACTED", "source_file": "C:\\Projects\\Arza\\ECommerce.API\\Controllers\\CartController.cs", "source_location": "L17", "weight": 1.0, "context": "field"}, {"source": "controllers_cartcontroller_cartcontroller", "target": "controllers_cartcontroller_cartcontroller_getuserid", "relation": "method", "confidence": "EXTRACTED", "source_file": "C:\\Projects\\Arza\\ECommerce.API\\Controllers\\CartController.cs", "source_location": "L26", "weight": 1.0}, {"source": "controllers_cartcontroller_cartcontroller", "target": "controllers_cartcontroller_cartcontroller_getsessionid", "relation": "method", "confidence": "EXTRACTED", "source_file": "C:\\Projects\\Arza\\ECommerce.API\\Controllers\\CartController.cs", "source_location": "L28", "weight": 1.0}, {"source": "controllers_cartcontroller_cartcontroller", "target": "controllers_cartcontroller_cartcontroller_getcachekey", "relation": "method", "confidence": "EXTRACTED", "source_file": "C:\\Projects\\Arza\\ECommerce.API\\Controllers\\CartController.cs", "source_location": "L42", "weight": 1.0}, {"source": "controllers_cartcontroller_cartcontroller", "target": "controllers_cartcontroller_cartcontroller_getcart", "relation": "method", "confidence": "EXTRACTED", "source_file": "C:\\Projects\\Arza\\ECommerce.API\\Controllers\\CartController.cs", "source_location": "L53", "weight": 1.0}, {"source": "controllers_cartcontroller_cartcontroller_getcart", "target": "task", "relation": "references", "confidence": "EXTRACTED", "source_file": "C:\\Projects\\Arza\\ECommerce.API\\Controllers\\CartController.cs", "source_location": "L53", "weight": 1.0, "context": "return_type"}, {"source": "controllers_cartcontroller_cartcontroller_getcart", "target": "actionresult", "relation": "references", "confidence": "EXTRACTED", "source_file": "C:\\Projects\\Arza\\ECommerce.API\\Controllers\\CartController.cs", "source_location": "L53", "weight": 1.0, "context": "generic_arg"}, {"source": "controllers_cartcontroller_cartcontroller_getcart", "target": "cartdto", "relation": "references", "confidence": "EXTRACTED", "source_file": "C:\\Projects\\Arza\\ECommerce.API\\Controllers\\CartController.cs", "source_location": "L53", "weight": 1.0, "context": "generic_arg"}, {"source": "controllers_cartcontroller_cartcontroller_getcart", "target": "httpget", "relation": "references", "confidence": "EXTRACTED", "source_file": "C:\\Projects\\Arza\\ECommerce.API\\Controllers\\CartController.cs", "source_location": "L53", "weight": 1.0, "context": "attribute"}, {"source": "controllers_cartcontroller_cartcontroller_getcart", "target": "responsecache", "relation": "references", "confidence": "EXTRACTED", "source_file": "C:\\Projects\\Arza\\ECommerce.API\\Controllers\\CartController.cs", "source_location": "L53", "weight": 1.0, "context": "attribute"}, {"source": "controllers_cartcontroller_cartcontroller", "target": "controllers_cartcontroller_cartcontroller_additem", "relation": "method", "confidence": "EXTRACTED", "source_file": "C:\\Projects\\Arza\\ECommerce.API\\Controllers\\CartController.cs", "source_location": "L73", "weight": 1.0}, {"source": "controllers_cartcontroller_cartcontroller_additem", "target": "addtocartdto", "relation": "references", "confidence": "EXTRACTED", "source_file": "C:\\Projects\\Arza\\ECommerce.API\\Controllers\\CartController.cs", "source_location": "L73", "weight": 1.0, "context": "parameter_type"}, {"source": "controllers_cartcontroller_cartcontroller_additem", "target": "task", "relation": "references", "confidence": "EXTRACTED", "source_file": "C:\\Projects\\Arza\\ECommerce.API\\Controllers\\CartController.cs", "source_location": "L73", "weight": 1.0, "context": "return_type"}, {"source": "controllers_cartcontroller_cartcontroller_additem", "target": "actionresult", "relation": "references", "confidence": "EXTRACTED", "source_file": "C:\\Projects\\Arza\\ECommerce.API\\Controllers\\CartController.cs", "source_location": "L73", "weight": 1.0, "context": "generic_arg"}, {"source": "controllers_cartcontroller_cartcontroller_additem", "target": "httppost", "relation": "references", "confidence": "EXTRACTED", "source_file": "C:\\Projects\\Arza\\ECommerce.API\\Controllers\\CartController.cs", "source_location": "L73", "weight": 1.0, "context": "attribute"}, {"source": "controllers_cartcontroller_cartcontroller", "target": "controllers_cartcontroller_cartcontroller_updateitem", "relation": "method", "confidence": "EXTRACTED", "source_file": "C:\\Projects\\Arza\\ECommerce.API\\Controllers\\CartController.cs", "source_location": "L94", "weight": 1.0}, {"source": "controllers_cartcontroller_cartcontroller_updateitem", "target": "updatecartitemdto", "relation": "references", "confidence": "EXTRACTED", "source_file": "C:\\Projects\\Arza\\ECommerce.API\\Controllers\\CartController.cs", "source_location": "L94", "weight": 1.0, "context": "parameter_type"}, {"source": "controllers_cartcontroller_cartcontroller_updateitem", "target": "task", "relation": "references", "confidence": "EXTRACTED", "source_file": "C:\\Projects\\Arza\\ECommerce.API\\Controllers\\CartController.cs", "source_location": "L94", "weight": 1.0, "context": "return_type"}, {"source": "controllers_cartcontroller_cartcontroller_updateitem", "target": "actionresult", "relation": "references", "confidence": "EXTRACTED", "source_file": "C:\\Projects\\Arza\\ECommerce.API\\Controllers\\CartController.cs", "source_location": "L94", "weight": 1.0, "context": "generic_arg"}, {"source": "controllers_cartcontroller_cartcontroller_updateitem", "target": "cartdto", "relation": "references", "confidence": "EXTRACTED", "source_file": "C:\\Projects\\Arza\\ECommerce.API\\Controllers\\CartController.cs", "source_location": "L94", "weight": 1.0, "context": "generic_arg"}, {"source": "controllers_cartcontroller_cartcontroller_updateitem", "target": "httppost", "relation": "references", "confidence": "EXTRACTED", "source_file": "C:\\Projects\\Arza\\ECommerce.API\\Controllers\\CartController.cs", "source_location": "L94", "weight": 1.0, "context": "attribute"}, {"source": "controllers_cartcontroller_cartcontroller", "target": "controllers_cartcontroller_cartcontroller_removeitem", "relation": "method", "confidence": "EXTRACTED", "source_file": "C:\\Projects\\Arza\\ECommerce.API\\Controllers\\CartController.cs", "source_location": "L119", "weight": 1.0}, {"source": "controllers_cartcontroller_cartcontroller_removeitem", "target": "task", "relation": "references", "confidence": "EXTRACTED", "source_file": "C:\\Projects\\Arza\\ECommerce.API\\Controllers\\CartController.cs", "source_location": "L119", "weight": 1.0, "context": "return_type"}, {"source": "controllers_cartcontroller_cartcontroller_removeitem", "target": "actionresult", "relation": "references", "confidence": "EXTRACTED", "source_file": "C:\\Projects\\Arza\\ECommerce.API\\Controllers\\CartController.cs", "source_location": "L119", "weight": 1.0, "context": "generic_arg"}, {"source": "controllers_cartcontroller_cartcontroller_removeitem", "target": "cartdto", "relation": "references", "confidence": "EXTRACTED", "source_file": "C:\\Projects\\Arza\\ECommerce.API\\Controllers\\CartController.cs", "source_location": "L119", "weight": 1.0, "context": "generic_arg"}, {"source": "controllers_cartcontroller_cartcontroller_removeitem", "target": "httpdelete", "relation": "references", "confidence": "EXTRACTED", "source_file": "C:\\Projects\\Arza\\ECommerce.API\\Controllers\\CartController.cs", "source_location": "L119", "weight": 1.0, "context": "attribute"}, {"source": "controllers_cartcontroller_cartcontroller", "target": "controllers_cartcontroller_cartcontroller_clearcart", "relation": "method", "confidence": "EXTRACTED", "source_file": "C:\\Projects\\Arza\\ECommerce.API\\Controllers\\CartController.cs", "source_location": "L135", "weight": 1.0}, {"source": "controllers_cartcontroller_cartcontroller_clearcart", "target": "task", "relation": "references", "confidence": "EXTRACTED", "source_file": "C:\\Projects\\Arza\\ECommerce.API\\Controllers\\CartController.cs", "source_location": "L135", "weight": 1.0, "context": "return_type"}, {"source": "controllers_cartcontroller_cartcontroller_clearcart", "target": "actionresult", "relation": "references", "confidence": "EXTRACTED", "source_file": "C:\\Projects\\Arza\\ECommerce.API\\Controllers\\CartController.cs", "source_location": "L135", "weight": 1.0, "context": "generic_arg"}, {"source": "controllers_cartcontroller_cartcontroller_clearcart", "target": "httpdelete", "relation": "references", "confidence": "EXTRACTED", "source_file": "C:\\Projects\\Arza\\ECommerce.API\\Controllers\\CartController.cs", "source_location": "L135", "weight": 1.0, "context": "attribute"}, {"source": "controllers_cartcontroller_cartcontroller", "target": "controllers_cartcontroller_cartcontroller_mergeguestcart", "relation": "method", "confidence": "EXTRACTED", "source_file": "C:\\Projects\\Arza\\ECommerce.API\\Controllers\\CartController.cs", "source_location": "L146", "weight": 1.0}, {"source": "controllers_cartcontroller_cartcontroller_mergeguestcart", "target": "task", "relation": "references", "confidence": "EXTRACTED", "source_file": "C:\\Projects\\Arza\\ECommerce.API\\Controllers\\CartController.cs", "source_location": "L146", "weight": 1.0, "context": "return_type"}, {"source": "controllers_cartcontroller_cartcontroller_mergeguestcart", "target": "actionresult", "relation": "references", "confidence": "EXTRACTED", "source_file": "C:\\Projects\\Arza\\ECommerce.API\\Controllers\\CartController.cs", "source_location": "L146", "weight": 1.0, "context": "generic_arg"}, {"source": "controllers_cartcontroller_cartcontroller_mergeguestcart", "target": "cartdto", "relation": "references", "confidence": "EXTRACTED", "source_file": "C:\\Projects\\Arza\\ECommerce.API\\Controllers\\CartController.cs", "source_location": "L146", "weight": 1.0, "context": "generic_arg"}, {"source": "controllers_cartcontroller_cartcontroller_mergeguestcart", "target": "httppost", "relation": "references", "confidence": "EXTRACTED", "source_file": "C:\\Projects\\Arza\\ECommerce.API\\Controllers\\CartController.cs", "source_location": "L146", "weight": 1.0, "context": "attribute"}, {"source": "controllers_cartcontroller_cartcontroller_getcachekey", "target": "controllers_cartcontroller_cartcontroller_getuserid", "relation": "calls", "context": "call", "confidence": "EXTRACTED", "source_file": "C:\\Projects\\Arza\\ECommerce.API\\Controllers\\CartController.cs", "source_location": "L44", "weight": 1.0}, {"source": "controllers_cartcontroller_cartcontroller_getcachekey", "target": "controllers_cartcontroller_cartcontroller_getsessionid", "relation": "calls", "context": "call", "confidence": "EXTRACTED", "source_file": "C:\\Projects\\Arza\\ECommerce.API\\Controllers\\CartController.cs", "source_location": "L47", "weight": 1.0}, {"source": "controllers_cartcontroller_cartcontroller_getcart", "target": "controllers_cartcontroller_cartcontroller_getcachekey", "relation": "calls", "context": "call", "confidence": "EXTRACTED", "source_file": "C:\\Projects\\Arza\\ECommerce.API\\Controllers\\CartController.cs", "source_location": "L57", "weight": 1.0}, {"source": "controllers_cartcontroller_cartcontroller_getcart", "target": "controllers_cartcontroller_cartcontroller_getuserid", "relation": "calls", "context": "call", "confidence": "EXTRACTED", "source_file": "C:\\Projects\\Arza\\ECommerce.API\\Controllers\\CartController.cs", "source_location": "L63", "weight": 1.0}, {"source": "controllers_cartcontroller_cartcontroller_getcart", "target": "controllers_cartcontroller_cartcontroller_getsessionid", "relation": "calls", "context": "call", "confidence": "EXTRACTED", "source_file": "C:\\Projects\\Arza\\ECommerce.API\\Controllers\\CartController.cs", "source_location": "L63", "weight": 1.0}, {"source": "controllers_cartcontroller_cartcontroller_additem", "target": "controllers_cartcontroller_cartcontroller_getuserid", "relation": "calls", "context": "call", "confidence": "EXTRACTED", "source_file": "C:\\Projects\\Arza\\ECommerce.API\\Controllers\\CartController.cs", "source_location": "L78", "weight": 1.0}, {"source": "controllers_cartcontroller_cartcontroller_additem", "target": "controllers_cartcontroller_cartcontroller_getsessionid", "relation": "calls", "context": "call", "confidence": "EXTRACTED", "source_file": "C:\\Projects\\Arza\\ECommerce.API\\Controllers\\CartController.cs", "source_location": "L78", "weight": 1.0}, {"source": "controllers_cartcontroller_cartcontroller_additem", "target": "controllers_cartcontroller_cartcontroller_getcachekey", "relation": "calls", "context": "call", "confidence": "EXTRACTED", "source_file": "C:\\Projects\\Arza\\ECommerce.API\\Controllers\\CartController.cs", "source_location": "L80", "weight": 1.0}, {"source": "controllers_cartcontroller_cartcontroller_updateitem", "target": "controllers_cartcontroller_cartcontroller_getuserid", "relation": "calls", "context": "call", "confidence": "EXTRACTED", "source_file": "C:\\Projects\\Arza\\ECommerce.API\\Controllers\\CartController.cs", "source_location": "L99", "weight": 1.0}, {"source": "controllers_cartcontroller_cartcontroller_updateitem", "target": "controllers_cartcontroller_cartcontroller_getsessionid", "relation": "calls", "context": "call", "confidence": "EXTRACTED", "source_file": "C:\\Projects\\Arza\\ECommerce.API\\Controllers\\CartController.cs", "source_location": "L99", "weight": 1.0}, {"source": "controllers_cartcontroller_cartcontroller_updateitem", "target": "controllers_cartcontroller_cartcontroller_getcachekey", "relation": "calls", "context": "call", "confidence": "EXTRACTED", "source_file": "C:\\Projects\\Arza\\ECommerce.API\\Controllers\\CartController.cs", "source_location": "L101", "weight": 1.0}, {"source": "controllers_cartcontroller_cartcontroller_removeitem", "target": "controllers_cartcontroller_cartcontroller_getuserid", "relation": "calls", "context": "call", "confidence": "EXTRACTED", "source_file": "C:\\Projects\\Arza\\ECommerce.API\\Controllers\\CartController.cs", "source_location": "L124", "weight": 1.0}, {"source": "controllers_cartcontroller_cartcontroller_removeitem", "target": "controllers_cartcontroller_cartcontroller_getsessionid", "relation": "calls", "context": "call", "confidence": "EXTRACTED", "source_file": "C:\\Projects\\Arza\\ECommerce.API\\Controllers\\CartController.cs", "source_location": "L124", "weight": 1.0}, {"source": "controllers_cartcontroller_cartcontroller_removeitem", "target": "controllers_cartcontroller_cartcontroller_getcachekey", "relation": "calls", "context": "call", "confidence": "EXTRACTED", "source_file": "C:\\Projects\\Arza\\ECommerce.API\\Controllers\\CartController.cs", "source_location": "L126", "weight": 1.0}, {"source": "controllers_cartcontroller_cartcontroller_clearcart", "target": "controllers_cartcontroller_cartcontroller_getuserid", "relation": "calls", "context": "call", "confidence": "EXTRACTED", "source_file": "C:\\Projects\\Arza\\ECommerce.API\\Controllers\\CartController.cs", "source_location": "L138", "weight": 1.0}, {"source": "controllers_cartcontroller_cartcontroller_clearcart", "target": "controllers_cartcontroller_cartcontroller_getsessionid", "relation": "calls", "context": "call", "confidence": "EXTRACTED", "source_file": "C:\\Projects\\Arza\\ECommerce.API\\Controllers\\CartController.cs", "source_location": "L138", "weight": 1.0}, {"source": "controllers_cartcontroller_cartcontroller_clearcart", "target": "controllers_cartcontroller_cartcontroller_getcachekey", "relation": "calls", "context": "call", "confidence": "EXTRACTED", "source_file": "C:\\Projects\\Arza\\ECommerce.API\\Controllers\\CartController.cs", "source_location": "L140", "weight": 1.0}, {"source": "controllers_cartcontroller_cartcontroller_mergeguestcart", "target": "controllers_cartcontroller_cartcontroller_getuserid", "relation": "calls", "context": "call", "confidence": "EXTRACTED", "source_file": "C:\\Projects\\Arza\\ECommerce.API\\Controllers\\CartController.cs", "source_location": "L151", "weight": 1.0}, {"source": "controllers_cartcontroller_cartcontroller_mergeguestcart", "target": "controllers_cartcontroller_cartcontroller_getcachekey", "relation": "calls", "context": "call", "confidence": "EXTRACTED", "source_file": "C:\\Projects\\Arza\\ECommerce.API\\Controllers\\CartController.cs", "source_location": "L156", "weight": 1.0}], "raw_calls": [{"caller_nid": "controllers_cartcontroller_cartcontroller_getuserid", "callee": "FindFirst", "is_member_call": true, "source_file": "C:\\Projects\\Arza\\ECommerce.API\\Controllers\\CartController.cs", "source_location": "L26"}, {"caller_nid": "controllers_cartcontroller_cartcontroller_getsessionid", "callee": "TryGetValue", "is_member_call": true, "source_file": "C:\\Projects\\Arza\\ECommerce.API\\Controllers\\CartController.cs", "source_location": "L31"}, {"caller_nid": "controllers_cartcontroller_cartcontroller_getsessionid", "callee": "Trim", "is_member_call": true, "source_file": "C:\\Projects\\Arza\\ECommerce.API\\Controllers\\CartController.cs", "source_location": "L33"}, {"caller_nid": "controllers_cartcontroller_cartcontroller_getsessionid", "callee": "ToString", "is_member_call": true, "source_file": "C:\\Projects\\Arza\\ECommerce.API\\Controllers\\CartController.cs", "source_location": "L33"}, {"caller_nid": "controllers_cartcontroller_cartcontroller_getsessionid", "callee": "IsNullOrEmpty", "is_member_call": true, "source_file": "C:\\Projects\\Arza\\ECommerce.API\\Controllers\\CartController.cs", "source_location": "L34"}, {"caller_nid": "controllers_cartcontroller_cartcontroller_getcachekey", "callee": "IsNullOrEmpty", "is_member_call": true, "source_file": "C:\\Projects\\Arza\\ECommerce.API\\Controllers\\CartController.cs", "source_location": "L45"}, {"caller_nid": "controllers_cartcontroller_cartcontroller_getcachekey", "callee": "IsNullOrEmpty", "is_member_call": true, "source_file": "C:\\Projects\\Arza\\ECommerce.API\\Controllers\\CartController.cs", "source_location": "L48"}, {"caller_nid": "controllers_cartcontroller_cartcontroller_getcart", "callee": "IsNullOrEmpty", "is_member_call": true, "source_file": "C:\\Projects\\Arza\\ECommerce.API\\Controllers\\CartController.cs", "source_location": "L58"}, {"caller_nid": "controllers_cartcontroller_cartcontroller_getcart", "callee": "TryGetValue", "is_member_call": true, "source_file": "C:\\Projects\\Arza\\ECommerce.API\\Controllers\\CartController.cs", "source_location": "L58"}, {"caller_nid": "controllers_cartcontroller_cartcontroller_getcart", "callee": "Ok", "is_member_call": false, "source_file": "C:\\Projects\\Arza\\ECommerce.API\\Controllers\\CartController.cs", "source_location": "L60"}, {"caller_nid": "controllers_cartcontroller_cartcontroller_getcart", "callee": "GetCartAsync", "is_member_call": true, "source_file": "C:\\Projects\\Arza\\ECommerce.API\\Controllers\\CartController.cs", "source_location": "L63"}, {"caller_nid": "controllers_cartcontroller_cartcontroller_getcart", "callee": "IsNullOrEmpty", "is_member_call": true, "source_file": "C:\\Projects\\Arza\\ECommerce.API\\Controllers\\CartController.cs", "source_location": "L65"}, {"caller_nid": "controllers_cartcontroller_cartcontroller_getcart", "callee": "Ok", "is_member_call": false, "source_file": "C:\\Projects\\Arza\\ECommerce.API\\Controllers\\CartController.cs", "source_location": "L70"}, {"caller_nid": "controllers_cartcontroller_cartcontroller_additem", "callee": "AddItemAsync", "is_member_call": true, "source_file": "C:\\Projects\\Arza\\ECommerce.API\\Controllers\\CartController.cs", "source_location": "L78"}, {"caller_nid": "controllers_cartcontroller_cartcontroller_additem", "callee": "IsNullOrEmpty", "is_member_call": true, "source_file": "C:\\Projects\\Arza\\ECommerce.API\\Controllers\\CartController.cs", "source_location": "L81"}, {"caller_nid": "controllers_cartcontroller_cartcontroller_additem", "callee": "Ok", "is_member_call": false, "source_file": "C:\\Projects\\Arza\\ECommerce.API\\Controllers\\CartController.cs", "source_location": "L86"}, {"caller_nid": "controllers_cartcontroller_cartcontroller_additem", "callee": "NotFound", "is_member_call": false, "source_file": "C:\\Projects\\Arza\\ECommerce.API\\Controllers\\CartController.cs", "source_location": "L90"}, {"caller_nid": "controllers_cartcontroller_cartcontroller_updateitem", "callee": "UpdateItemAsync", "is_member_call": true, "source_file": "C:\\Projects\\Arza\\ECommerce.API\\Controllers\\CartController.cs", "source_location": "L99"}, {"caller_nid": "controllers_cartcontroller_cartcontroller_updateitem", "callee": "IsNullOrEmpty", "is_member_call": true, "source_file": "C:\\Projects\\Arza\\ECommerce.API\\Controllers\\CartController.cs", "source_location": "L102"}, {"caller_nid": "controllers_cartcontroller_cartcontroller_updateitem", "callee": "Ok", "is_member_call": false, "source_file": "C:\\Projects\\Arza\\ECommerce.API\\Controllers\\CartController.cs", "source_location": "L107"}, {"caller_nid": "controllers_cartcontroller_cartcontroller_updateitem", "callee": "NotFound", "is_member_call": false, "source_file": "C:\\Projects\\Arza\\ECommerce.API\\Controllers\\CartController.cs", "source_location": "L111"}, {"caller_nid": "controllers_cartcontroller_cartcontroller_updateitem", "callee": "Unauthorized", "is_member_call": false, "source_file": "C:\\Projects\\Arza\\ECommerce.API\\Controllers\\CartController.cs", "source_location": "L115"}, {"caller_nid": "controllers_cartcontroller_cartcontroller_removeitem", "callee": "LogInformation", "is_member_call": true, "source_file": "C:\\Projects\\Arza\\ECommerce.API\\Controllers\\CartController.cs", "source_location": "L122"}, {"caller_nid": "controllers_cartcontroller_cartcontroller_removeitem", "callee": "RemoveItemAsync", "is_member_call": true, "source_file": "C:\\Projects\\Arza\\ECommerce.API\\Controllers\\CartController.cs", "source_location": "L124"}, {"caller_nid": "controllers_cartcontroller_cartcontroller_removeitem", "callee": "IsNullOrEmpty", "is_member_call": true, "source_file": "C:\\Projects\\Arza\\ECommerce.API\\Controllers\\CartController.cs", "source_location": "L127"}, {"caller_nid": "controllers_cartcontroller_cartcontroller_removeitem", "callee": "Ok", "is_member_call": false, "source_file": "C:\\Projects\\Arza\\ECommerce.API\\Controllers\\CartController.cs", "source_location": "L132"}, {"caller_nid": "controllers_cartcontroller_cartcontroller_clearcart", "callee": "ClearCartAsync", "is_member_call": true, "source_file": "C:\\Projects\\Arza\\ECommerce.API\\Controllers\\CartController.cs", "source_location": "L138"}, {"caller_nid": "controllers_cartcontroller_cartcontroller_clearcart", "callee": "IsNullOrEmpty", "is_member_call": true, "source_file": "C:\\Projects\\Arza\\ECommerce.API\\Controllers\\CartController.cs", "source_location": "L141"}, {"caller_nid": "controllers_cartcontroller_cartcontroller_clearcart", "callee": "Remove", "is_member_call": true, "source_file": "C:\\Projects\\Arza\\ECommerce.API\\Controllers\\CartController.cs", "source_location": "L141"}, {"caller_nid": "controllers_cartcontroller_cartcontroller_clearcart", "callee": "NoContent", "is_member_call": false, "source_file": "C:\\Projects\\Arza\\ECommerce.API\\Controllers\\CartController.cs", "source_location": "L143"}, {"caller_nid": "controllers_cartcontroller_cartcontroller_mergeguestcart", "callee": "IsNullOrEmpty", "is_member_call": true, "source_file": "C:\\Projects\\Arza\\ECommerce.API\\Controllers\\CartController.cs", "source_location": "L149"}, {"caller_nid": "controllers_cartcontroller_cartcontroller_mergeguestcart", "callee": "BadRequest", "is_member_call": false, "source_file": "C:\\Projects\\Arza\\ECommerce.API\\Controllers\\CartController.cs", "source_location": "L149"}, {"caller_nid": "controllers_cartcontroller_cartcontroller_mergeguestcart", "callee": "IsNullOrEmpty", "is_member_call": true, "source_file": "C:\\Projects\\Arza\\ECommerce.API\\Controllers\\CartController.cs", "source_location": "L152"}, {"caller_nid": "controllers_cartcontroller_cartcontroller_mergeguestcart", "callee": "Unauthorized", "is_member_call": false, "source_file": "C:\\Projects\\Arza\\ECommerce.API\\Controllers\\CartController.cs", "source_location": "L152"}, {"caller_nid": "controllers_cartcontroller_cartcontroller_mergeguestcart", "callee": "MergeGuestCartAsync", "is_member_call": true, "source_file": "C:\\Projects\\Arza\\ECommerce.API\\Controllers\\CartController.cs", "source_location": "L154"}, {"caller_nid": "controllers_cartcontroller_cartcontroller_mergeguestcart", "callee": "IsNullOrEmpty", "is_member_call": true, "source_file": "C:\\Projects\\Arza\\ECommerce.API\\Controllers\\CartController.cs", "source_location": "L157"}, {"caller_nid": "controllers_cartcontroller_cartcontroller_mergeguestcart", "callee": "Ok", "is_member_call": false, "source_file": "C:\\Projects\\Arza\\ECommerce.API\\Controllers\\CartController.cs", "source_location": "L162"}]}