{"nodes": [{"id": "c_projects_arza_ecommerce_api_controllers_adminuserscontroller_cs", "label": "AdminUsersController.cs", "file_type": "code", "source_file": "C:\\Projects\\Arza\\ECommerce.API\\Controllers\\AdminUsersController.cs", "source_location": "L1"}, {"id": "controllers_adminuserscontroller_adminuserscontroller", "label": "AdminUsersController", "file_type": "code", "source_file": "C:\\Projects\\Arza\\ECommerce.API\\Controllers\\AdminUsersController.cs", "source_location": "L12"}, {"id": "controllerbase", "label": "ControllerBase", "file_type": "code", "source_file": "", "source_location": ""}, {"id": "usermanager", "label": "UserManager", "file_type": "code", "source_file": "C:\\Projects\\Arza\\ECommerce.API\\Controllers\\AdminUsersController.cs", "source_location": "L18"}, {"id": "applicationdbcontext", "label": "ApplicationDbContext", "file_type": "code", "source_file": "C:\\Projects\\Arza\\ECommerce.API\\Controllers\\AdminUsersController.cs", "source_location": "L19"}, {"id": "passwordprotector", "label": "PasswordProtector", "file_type": "code", "source_file": "C:\\Projects\\Arza\\ECommerce.API\\Controllers\\AdminUsersController.cs", "source_location": "L20"}, {"id": "controllers_adminuserscontroller_adminuserscontroller_getcurrentuserid", "label": ".GetCurrentUserId()", "file_type": "code", "source_file": "C:\\Projects\\Arza\\ECommerce.API\\Controllers\\AdminUsersController.cs", "source_location": "L29"}, {"id": "controllers_adminuserscontroller_adminuserscontroller_getclientip", "label": ".GetClientIp()", "file_type": "code", "source_file": "C:\\Projects\\Arza\\ECommerce.API\\Controllers\\AdminUsersController.cs", "source_location": "L30"}, {"id": "controllers_adminuserscontroller_adminuserscontroller_logactivityasync", "label": ".LogActivityAsync()", "file_type": "code", "source_file": "C:\\Projects\\Arza\\ECommerce.API\\Controllers\\AdminUsersController.cs", "source_location": "L32"}, {"id": "task", "label": "Task", "file_type": "code", "source_file": "C:\\Projects\\Arza\\ECommerce.API\\Controllers\\AdminUsersController.cs", "source_location": "L32"}, {"id": "controllers_adminuserscontroller_adminuserscontroller_getadminusers", "label": ".GetAdminUsers()", "file_type": "code", "source_file": "C:\\Projects\\Arza\\ECommerce.API\\Controllers\\AdminUsersController.cs", "source_location": "L47"}, {"id": "actionresult", "label": "ActionResult", "file_type": "code", "source_file": "C:\\Projects\\Arza\\ECommerce.API\\Controllers\\AdminUsersController.cs", "source_location": "L47"}, {"id": "ienumerable", "label": "IEnumerable", "file_type": "code", "source_file": "C:\\Projects\\Arza\\ECommerce.API\\Controllers\\AdminUsersController.cs", "source_location": "L47"}, {"id": "httpget", "label": "HttpGet", "file_type": "code", "source_file": "C:\\Projects\\Arza\\ECommerce.API\\Controllers\\AdminUsersController.cs", "source_location": "L47"}, {"id": "controllers_adminuserscontroller_adminuserscontroller_createadminuser", "label": ".CreateAdminUser()", "file_type": "code", "source_file": "C:\\Projects\\Arza\\ECommerce.API\\Controllers\\AdminUsersController.cs", "source_location": "L73"}, {"id": "createadminuserdto", "label": "CreateAdminUserDto", "file_type": "code", "source_file": "C:\\Projects\\Arza\\ECommerce.API\\Controllers\\AdminUsersController.cs", "source_location": "L73"}, {"id": "httppost", "label": "HttpPost", "file_type": "code", "source_file": "C:\\Projects\\Arza\\ECommerce.API\\Controllers\\AdminUsersController.cs", "source_location": "L73"}, {"id": "authorize", "label": "Authorize", "file_type": "code", "source_file": "C:\\Projects\\Arza\\ECommerce.API\\Controllers\\AdminUsersController.cs", "source_location": "L73"}, {"id": "controllers_adminuserscontroller_adminuserscontroller_updateadminuser", "label": ".UpdateAdminUser()", "file_type": "code", "source_file": "C:\\Projects\\Arza\\ECommerce.API\\Controllers\\AdminUsersController.cs", "source_location": "L139"}, {"id": "updateadminuserdto", "label": "UpdateAdminUserDto", "file_type": "code", "source_file": "C:\\Projects\\Arza\\ECommerce.API\\Controllers\\AdminUsersController.cs", "source_location": "L139"}, {"id": "controllers_adminuserscontroller_adminuserscontroller_resetadminuserpassword", "label": ".ResetAdminUserPassword()", "file_type": "code", "source_file": "C:\\Projects\\Arza\\ECommerce.API\\Controllers\\AdminUsersController.cs", "source_location": "L227"}, {"id": "resetpassworddto", "label": "ResetPasswordDto", "file_type": "code", "source_file": "C:\\Projects\\Arza\\ECommerce.API\\Controllers\\AdminUsersController.cs", "source_location": "L227"}, {"id": "controllers_adminuserscontroller_adminuserscontroller_getuserpassword", "label": ".GetUserPassword()", "file_type": "code", "source_file": "C:\\Projects\\Arza\\ECommerce.API\\Controllers\\AdminUsersController.cs", "source_location": "L253"}, {"id": "controllers_adminuserscontroller_adminuserscontroller_toggleuseractive", "label": ".ToggleUserActive()", "file_type": "code", "source_file": "C:\\Projects\\Arza\\ECommerce.API\\Controllers\\AdminUsersController.cs", "source_location": "L270"}, {"id": "controllers_adminuserscontroller_adminuserscontroller_getactivitylog", "label": ".GetActivityLog()", "file_type": "code", "source_file": "C:\\Projects\\Arza\\ECommerce.API\\Controllers\\AdminUsersController.cs", "source_location": "L292"}, {"id": "controllers_adminuserscontroller_createadminuserdto", "label": "CreateAdminUserDto", "file_type": "code", "source_file": "C:\\Projects\\Arza\\ECommerce.API\\Controllers\\AdminUsersController.cs", "source_location": "L318"}, {"id": "controllers_adminuserscontroller_updateadminuserdto", "label": "UpdateAdminUserDto", "file_type": "code", "source_file": "C:\\Projects\\Arza\\ECommerce.API\\Controllers\\AdminUsersController.cs", "source_location": "L329"}, {"id": "controllers_adminuserscontroller_resetpassworddto", "label": "ResetPasswordDto", "file_type": "code", "source_file": "C:\\Projects\\Arza\\ECommerce.API\\Controllers\\AdminUsersController.cs", "source_location": "L340"}], "edges": [{"source": "c_projects_arza_ecommerce_api_controllers_adminuserscontroller_cs", "target": "helpers", "relation": "imports", "context": "import", "confidence": "EXTRACTED", "source_file": "C:\\Projects\\Arza\\ECommerce.API\\Controllers\\AdminUsersController.cs", "source_location": "L1", "weight": 1.0}, {"source": "c_projects_arza_ecommerce_api_controllers_adminuserscontroller_cs", "target": "entities", "relation": "imports", "context": "import", "confidence": "EXTRACTED", "source_file": "C:\\Projects\\Arza\\ECommerce.API\\Controllers\\AdminUsersController.cs", "source_location": "L2", "weight": 1.0}, {"source": "c_projects_arza_ecommerce_api_controllers_adminuserscontroller_cs", "target": "data", "relation": "imports", "context": "import", "confidence": "EXTRACTED", "source_file": "C:\\Projects\\Arza\\ECommerce.API\\Controllers\\AdminUsersController.cs", "source_location": "L3", "weight": 1.0}, {"source": "c_projects_arza_ecommerce_api_controllers_adminuserscontroller_cs", "target": "authorization", "relation": "imports", "context": "import", "confidence": "EXTRACTED", "source_file": "C:\\Projects\\Arza\\ECommerce.API\\Controllers\\AdminUsersController.cs", "source_location": "L4", "weight": 1.0}, {"source": "c_projects_arza_ecommerce_api_controllers_adminuserscontroller_cs", "target": "identity", "relation": "imports", "context": "import", "confidence": "EXTRACTED", "source_file": "C:\\Projects\\Arza\\ECommerce.API\\Controllers\\AdminUsersController.cs", "source_location": "L5", "weight": 1.0}, {"source": "c_projects_arza_ecommerce_api_controllers_adminuserscontroller_cs", "target": "mvc", "relation": "imports", "context": "import", "confidence": "EXTRACTED", "source_file": "C:\\Projects\\Arza\\ECommerce.API\\Controllers\\AdminUsersController.cs", "source_location": "L6", "weight": 1.0}, {"source": "c_projects_arza_ecommerce_api_controllers_adminuserscontroller_cs", "target": "entityframeworkcore", "relation": "imports", "context": "import", "confidence": "EXTRACTED", "source_file": "C:\\Projects\\Arza\\ECommerce.API\\Controllers\\AdminUsersController.cs", "source_location": "L7", "weight": 1.0}, {"source": "c_projects_arza_ecommerce_api_controllers_adminuserscontroller_cs", "target": "claims", "relation": "imports", "context": "import", "confidence": "EXTRACTED", "source_file": "C:\\Projects\\Arza\\ECommerce.API\\Controllers\\AdminUsersController.cs", "source_location": "L8", "weight": 1.0}, {"source": "c_projects_arza_ecommerce_api_controllers_adminuserscontroller_cs", "target": "controllers_adminuserscontroller_adminuserscontroller", "relation": "contains", "confidence": "EXTRACTED", "source_file": "C:\\Projects\\Arza\\ECommerce.API\\Controllers\\AdminUsersController.cs", "source_location": "L12", "weight": 1.0}, {"source": "controllers_adminuserscontroller_adminuserscontroller", "target": "controllerbase", "relation": "inherits", "confidence": "EXTRACTED", "source_file": "C:\\Projects\\Arza\\ECommerce.API\\Controllers\\AdminUsersController.cs", "source_location": "L12", "weight": 1.0}, {"source": "controllers_adminuserscontroller_adminuserscontroller", "target": "usermanager", "relation": "references", "confidence": "EXTRACTED", "source_file": "C:\\Projects\\Arza\\ECommerce.API\\Controllers\\AdminUsersController.cs", "source_location": "L18", "weight": 1.0, "context": "field"}, {"source": "controllers_adminuserscontroller_adminuserscontroller", "target": "applicationdbcontext", "relation": "references", "confidence": "EXTRACTED", "source_file": "C:\\Projects\\Arza\\ECommerce.API\\Controllers\\AdminUsersController.cs", "source_location": "L19", "weight": 1.0, "context": "field"}, {"source": "controllers_adminuserscontroller_adminuserscontroller", "target": "passwordprotector", "relation": "references", "confidence": "EXTRACTED", "source_file": "C:\\Projects\\Arza\\ECommerce.API\\Controllers\\AdminUsersController.cs", "source_location": "L20", "weight": 1.0, "context": "field"}, {"source": "controllers_adminuserscontroller_adminuserscontroller", "target": "controllers_adminuserscontroller_adminuserscontroller_getcurrentuserid", "relation": "method", "confidence": "EXTRACTED", "source_file": "C:\\Projects\\Arza\\ECommerce.API\\Controllers\\AdminUsersController.cs", "source_location": "L29", "weight": 1.0}, {"source": "controllers_adminuserscontroller_adminuserscontroller", "target": "controllers_adminuserscontroller_adminuserscontroller_getclientip", "relation": "method", "confidence": "EXTRACTED", "source_file": "C:\\Projects\\Arza\\ECommerce.API\\Controllers\\AdminUsersController.cs", "source_location": "L30", "weight": 1.0}, {"source": "controllers_adminuserscontroller_adminuserscontroller", "target": "controllers_adminuserscontroller_adminuserscontroller_logactivityasync", "relation": "method", "confidence": "EXTRACTED", "source_file": "C:\\Projects\\Arza\\ECommerce.API\\Controllers\\AdminUsersController.cs", "source_location": "L32", "weight": 1.0}, {"source": "controllers_adminuserscontroller_adminuserscontroller_logactivityasync", "target": "task", "relation": "references", "confidence": "EXTRACTED", "source_file": "C:\\Projects\\Arza\\ECommerce.API\\Controllers\\AdminUsersController.cs", "source_location": "L32", "weight": 1.0, "context": "return_type"}, {"source": "controllers_adminuserscontroller_adminuserscontroller", "target": "controllers_adminuserscontroller_adminuserscontroller_getadminusers", "relation": "method", "confidence": "EXTRACTED", "source_file": "C:\\Projects\\Arza\\ECommerce.API\\Controllers\\AdminUsersController.cs", "source_location": "L47", "weight": 1.0}, {"source": "controllers_adminuserscontroller_adminuserscontroller_getadminusers", "target": "task", "relation": "references", "confidence": "EXTRACTED", "source_file": "C:\\Projects\\Arza\\ECommerce.API\\Controllers\\AdminUsersController.cs", "source_location": "L47", "weight": 1.0, "context": "return_type"}, {"source": "controllers_adminuserscontroller_adminuserscontroller_getadminusers", "target": "actionresult", "relation": "references", "confidence": "EXTRACTED", "source_file": "C:\\Projects\\Arza\\ECommerce.API\\Controllers\\AdminUsersController.cs", "source_location": "L47", "weight": 1.0, "context": "generic_arg"}, {"source": "controllers_adminuserscontroller_adminuserscontroller_getadminusers", "target": "ienumerable", "relation": "references", "confidence": "EXTRACTED", "source_file": "C:\\Projects\\Arza\\ECommerce.API\\Controllers\\AdminUsersController.cs", "source_location": "L47", "weight": 1.0, "context": "generic_arg"}, {"source": "controllers_adminuserscontroller_adminuserscontroller_getadminusers", "target": "httpget", "relation": "references", "confidence": "EXTRACTED", "source_file": "C:\\Projects\\Arza\\ECommerce.API\\Controllers\\AdminUsersController.cs", "source_location": "L47", "weight": 1.0, "context": "attribute"}, {"source": "controllers_adminuserscontroller_adminuserscontroller", "target": "controllers_adminuserscontroller_adminuserscontroller_createadminuser", "relation": "method", "confidence": "EXTRACTED", "source_file": "C:\\Projects\\Arza\\ECommerce.API\\Controllers\\AdminUsersController.cs", "source_location": "L73", "weight": 1.0}, {"source": "controllers_adminuserscontroller_adminuserscontroller_createadminuser", "target": "createadminuserdto", "relation": "references", "confidence": "EXTRACTED", "source_file": "C:\\Projects\\Arza\\ECommerce.API\\Controllers\\AdminUsersController.cs", "source_location": "L73", "weight": 1.0, "context": "parameter_type"}, {"source": "controllers_adminuserscontroller_adminuserscontroller_createadminuser", "target": "task", "relation": "references", "confidence": "EXTRACTED", "source_file": "C:\\Projects\\Arza\\ECommerce.API\\Controllers\\AdminUsersController.cs", "source_location": "L73", "weight": 1.0, "context": "return_type"}, {"source": "controllers_adminuserscontroller_adminuserscontroller_createadminuser", "target": "actionresult", "relation": "references", "confidence": "EXTRACTED", "source_file": "C:\\Projects\\Arza\\ECommerce.API\\Controllers\\AdminUsersController.cs", "source_location": "L73", "weight": 1.0, "context": "generic_arg"}, {"source": "controllers_adminuserscontroller_adminuserscontroller_createadminuser", "target": "httppost", "relation": "references", "confidence": "EXTRACTED", "source_file": "C:\\Projects\\Arza\\ECommerce.API\\Controllers\\AdminUsersController.cs", "source_location": "L73", "weight": 1.0, "context": "attribute"}, {"source": "controllers_adminuserscontroller_adminuserscontroller_createadminuser", "target": "authorize", "relation": "references", "confidence": "EXTRACTED", "source_file": "C:\\Projects\\Arza\\ECommerce.API\\Controllers\\AdminUsersController.cs", "source_location": "L73", "weight": 1.0, "context": "attribute"}, {"source": "controllers_adminuserscontroller_adminuserscontroller", "target": "controllers_adminuserscontroller_adminuserscontroller_updateadminuser", "relation": "method", "confidence": "EXTRACTED", "source_file": "C:\\Projects\\Arza\\ECommerce.API\\Controllers\\AdminUsersController.cs", "source_location": "L139", "weight": 1.0}, {"source": "controllers_adminuserscontroller_adminuserscontroller_updateadminuser", "target": "updateadminuserdto", "relation": "references", "confidence": "EXTRACTED", "source_file": "C:\\Projects\\Arza\\ECommerce.API\\Controllers\\AdminUsersController.cs", "source_location": "L139", "weight": 1.0, "context": "parameter_type"}, {"source": "controllers_adminuserscontroller_adminuserscontroller_updateadminuser", "target": "task", "relation": "references", "confidence": "EXTRACTED", "source_file": "C:\\Projects\\Arza\\ECommerce.API\\Controllers\\AdminUsersController.cs", "source_location": "L139", "weight": 1.0, "context": "return_type"}, {"source": "controllers_adminuserscontroller_adminuserscontroller_updateadminuser", "target": "actionresult", "relation": "references", "confidence": "EXTRACTED", "source_file": "C:\\Projects\\Arza\\ECommerce.API\\Controllers\\AdminUsersController.cs", "source_location": "L139", "weight": 1.0, "context": "generic_arg"}, {"source": "controllers_adminuserscontroller_adminuserscontroller_updateadminuser", "target": "httppost", "relation": "references", "confidence": "EXTRACTED", "source_file": "C:\\Projects\\Arza\\ECommerce.API\\Controllers\\AdminUsersController.cs", "source_location": "L139", "weight": 1.0, "context": "attribute"}, {"source": "controllers_adminuserscontroller_adminuserscontroller_updateadminuser", "target": "authorize", "relation": "references", "confidence": "EXTRACTED", "source_file": "C:\\Projects\\Arza\\ECommerce.API\\Controllers\\AdminUsersController.cs", "source_location": "L139", "weight": 1.0, "context": "attribute"}, {"source": "controllers_adminuserscontroller_adminuserscontroller", "target": "controllers_adminuserscontroller_adminuserscontroller_resetadminuserpassword", "relation": "method", "confidence": "EXTRACTED", "source_file": "C:\\Projects\\Arza\\ECommerce.API\\Controllers\\AdminUsersController.cs", "source_location": "L227", "weight": 1.0}, {"source": "controllers_adminuserscontroller_adminuserscontroller_resetadminuserpassword", "target": "resetpassworddto", "relation": "references", "confidence": "EXTRACTED", "source_file": "C:\\Projects\\Arza\\ECommerce.API\\Controllers\\AdminUsersController.cs", "source_location": "L227", "weight": 1.0, "context": "parameter_type"}, {"source": "controllers_adminuserscontroller_adminuserscontroller_resetadminuserpassword", "target": "task", "relation": "references", "confidence": "EXTRACTED", "source_file": "C:\\Projects\\Arza\\ECommerce.API\\Controllers\\AdminUsersController.cs", "source_location": "L227", "weight": 1.0, "context": "return_type"}, {"source": "controllers_adminuserscontroller_adminuserscontroller_resetadminuserpassword", "target": "actionresult", "relation": "references", "confidence": "EXTRACTED", "source_file": "C:\\Projects\\Arza\\ECommerce.API\\Controllers\\AdminUsersController.cs", "source_location": "L227", "weight": 1.0, "context": "generic_arg"}, {"source": "controllers_adminuserscontroller_adminuserscontroller_resetadminuserpassword", "target": "httppost", "relation": "references", "confidence": "EXTRACTED", "source_file": "C:\\Projects\\Arza\\ECommerce.API\\Controllers\\AdminUsersController.cs", "source_location": "L227", "weight": 1.0, "context": "attribute"}, {"source": "controllers_adminuserscontroller_adminuserscontroller_resetadminuserpassword", "target": "authorize", "relation": "references", "confidence": "EXTRACTED", "source_file": "C:\\Projects\\Arza\\ECommerce.API\\Controllers\\AdminUsersController.cs", "source_location": "L227", "weight": 1.0, "context": "attribute"}, {"source": "controllers_adminuserscontroller_adminuserscontroller", "target": "controllers_adminuserscontroller_adminuserscontroller_getuserpassword", "relation": "method", "confidence": "EXTRACTED", "source_file": "C:\\Projects\\Arza\\ECommerce.API\\Controllers\\AdminUsersController.cs", "source_location": "L253", "weight": 1.0}, {"source": "controllers_adminuserscontroller_adminuserscontroller_getuserpassword", "target": "task", "relation": "references", "confidence": "EXTRACTED", "source_file": "C:\\Projects\\Arza\\ECommerce.API\\Controllers\\AdminUsersController.cs", "source_location": "L253", "weight": 1.0, "context": "return_type"}, {"source": "controllers_adminuserscontroller_adminuserscontroller_getuserpassword", "target": "actionresult", "relation": "references", "confidence": "EXTRACTED", "source_file": "C:\\Projects\\Arza\\ECommerce.API\\Controllers\\AdminUsersController.cs", "source_location": "L253", "weight": 1.0, "context": "generic_arg"}, {"source": "controllers_adminuserscontroller_adminuserscontroller_getuserpassword", "target": "httpget", "relation": "references", "confidence": "EXTRACTED", "source_file": "C:\\Projects\\Arza\\ECommerce.API\\Controllers\\AdminUsersController.cs", "source_location": "L253", "weight": 1.0, "context": "attribute"}, {"source": "controllers_adminuserscontroller_adminuserscontroller_getuserpassword", "target": "authorize", "relation": "references", "confidence": "EXTRACTED", "source_file": "C:\\Projects\\Arza\\ECommerce.API\\Controllers\\AdminUsersController.cs", "source_location": "L253", "weight": 1.0, "context": "attribute"}, {"source": "controllers_adminuserscontroller_adminuserscontroller", "target": "controllers_adminuserscontroller_adminuserscontroller_toggleuseractive", "relation": "method", "confidence": "EXTRACTED", "source_file": "C:\\Projects\\Arza\\ECommerce.API\\Controllers\\AdminUsersController.cs", "source_location": "L270", "weight": 1.0}, {"source": "controllers_adminuserscontroller_adminuserscontroller_toggleuseractive", "target": "task", "relation": "references", "confidence": "EXTRACTED", "source_file": "C:\\Projects\\Arza\\ECommerce.API\\Controllers\\AdminUsersController.cs", "source_location": "L270", "weight": 1.0, "context": "return_type"}, {"source": "controllers_adminuserscontroller_adminuserscontroller_toggleuseractive", "target": "actionresult", "relation": "references", "confidence": "EXTRACTED", "source_file": "C:\\Projects\\Arza\\ECommerce.API\\Controllers\\AdminUsersController.cs", "source_location": "L270", "weight": 1.0, "context": "generic_arg"}, {"source": "controllers_adminuserscontroller_adminuserscontroller_toggleuseractive", "target": "httppost", "relation": "references", "confidence": "EXTRACTED", "source_file": "C:\\Projects\\Arza\\ECommerce.API\\Controllers\\AdminUsersController.cs", "source_location": "L270", "weight": 1.0, "context": "attribute"}, {"source": "controllers_adminuserscontroller_adminuserscontroller_toggleuseractive", "target": "authorize", "relation": "references", "confidence": "EXTRACTED", "source_file": "C:\\Projects\\Arza\\ECommerce.API\\Controllers\\AdminUsersController.cs", "source_location": "L270", "weight": 1.0, "context": "attribute"}, {"source": "controllers_adminuserscontroller_adminuserscontroller", "target": "controllers_adminuserscontroller_adminuserscontroller_getactivitylog", "relation": "method", "confidence": "EXTRACTED", "source_file": "C:\\Projects\\Arza\\ECommerce.API\\Controllers\\AdminUsersController.cs", "source_location": "L292", "weight": 1.0}, {"source": "controllers_adminuserscontroller_adminuserscontroller_getactivitylog", "target": "task", "relation": "references", "confidence": "EXTRACTED", "source_file": "C:\\Projects\\Arza\\ECommerce.API\\Controllers\\AdminUsersController.cs", "source_location": "L292", "weight": 1.0, "context": "return_type"}, {"source": "controllers_adminuserscontroller_adminuserscontroller_getactivitylog", "target": "actionresult", "relation": "references", "confidence": "EXTRACTED", "source_file": "C:\\Projects\\Arza\\ECommerce.API\\Controllers\\AdminUsersController.cs", "source_location": "L292", "weight": 1.0, "context": "generic_arg"}, {"source": "controllers_adminuserscontroller_adminuserscontroller_getactivitylog", "target": "httpget", "relation": "references", "confidence": "EXTRACTED", "source_file": "C:\\Projects\\Arza\\ECommerce.API\\Controllers\\AdminUsersController.cs", "source_location": "L292", "weight": 1.0, "context": "attribute"}, {"source": "controllers_adminuserscontroller_adminuserscontroller_getactivitylog", "target": "authorize", "relation": "references", "confidence": "EXTRACTED", "source_file": "C:\\Projects\\Arza\\ECommerce.API\\Controllers\\AdminUsersController.cs", "source_location": "L292", "weight": 1.0, "context": "attribute"}, {"source": "c_projects_arza_ecommerce_api_controllers_adminuserscontroller_cs", "target": "controllers_adminuserscontroller_createadminuserdto", "relation": "contains", "confidence": "EXTRACTED", "source_file": "C:\\Projects\\Arza\\ECommerce.API\\Controllers\\AdminUsersController.cs", "source_location": "L318", "weight": 1.0}, {"source": "c_projects_arza_ecommerce_api_controllers_adminuserscontroller_cs", "target": "controllers_adminuserscontroller_updateadminuserdto", "relation": "contains", "confidence": "EXTRACTED", "source_file": "C:\\Projects\\Arza\\ECommerce.API\\Controllers\\AdminUsersController.cs", "source_location": "L329", "weight": 1.0}, {"source": "c_projects_arza_ecommerce_api_controllers_adminuserscontroller_cs", "target": "controllers_adminuserscontroller_resetpassworddto", "relation": "contains", "confidence": "EXTRACTED", "source_file": "C:\\Projects\\Arza\\ECommerce.API\\Controllers\\AdminUsersController.cs", "source_location": "L340", "weight": 1.0}, {"source": "controllers_adminuserscontroller_adminuserscontroller_logactivityasync", "target": "controllers_adminuserscontroller_adminuserscontroller_getclientip", "relation": "calls", "context": "call", "confidence": "EXTRACTED", "source_file": "C:\\Projects\\Arza\\ECommerce.API\\Controllers\\AdminUsersController.cs", "source_location": "L39", "weight": 1.0}, {"source": "controllers_adminuserscontroller_adminuserscontroller_logactivityasync", "target": "controllers_adminuserscontroller_adminuserscontroller_getcurrentuserid", "relation": "calls", "context": "call", "confidence": "EXTRACTED", "source_file": "C:\\Projects\\Arza\\ECommerce.API\\Controllers\\AdminUsersController.cs", "source_location": "L40", "weight": 1.0}, {"source": "controllers_adminuserscontroller_adminuserscontroller_createadminuser", "target": "controllers_adminuserscontroller_adminuserscontroller_logactivityasync", "relation": "calls", "context": "call", "confidence": "EXTRACTED", "source_file": "C:\\Projects\\Arza\\ECommerce.API\\Controllers\\AdminUsersController.cs", "source_location": "L119", "weight": 1.0}, {"source": "controllers_adminuserscontroller_adminuserscontroller_updateadminuser", "target": "controllers_adminuserscontroller_adminuserscontroller_logactivityasync", "relation": "calls", "context": "call", "confidence": "EXTRACTED", "source_file": "C:\\Projects\\Arza\\ECommerce.API\\Controllers\\AdminUsersController.cs", "source_location": "L222", "weight": 1.0}, {"source": "controllers_adminuserscontroller_adminuserscontroller_resetadminuserpassword", "target": "controllers_adminuserscontroller_adminuserscontroller_logactivityasync", "relation": "calls", "context": "call", "confidence": "EXTRACTED", "source_file": "C:\\Projects\\Arza\\ECommerce.API\\Controllers\\AdminUsersController.cs", "source_location": "L248", "weight": 1.0}, {"source": "controllers_adminuserscontroller_adminuserscontroller_getuserpassword", "target": "controllers_adminuserscontroller_adminuserscontroller_logactivityasync", "relation": "calls", "context": "call", "confidence": "EXTRACTED", "source_file": "C:\\Projects\\Arza\\ECommerce.API\\Controllers\\AdminUsersController.cs", "source_location": "L265", "weight": 1.0}, {"source": "controllers_adminuserscontroller_adminuserscontroller_toggleuseractive", "target": "controllers_adminuserscontroller_adminuserscontroller_getcurrentuserid", "relation": "calls", "context": "call", "confidence": "EXTRACTED", "source_file": "C:\\Projects\\Arza\\ECommerce.API\\Controllers\\AdminUsersController.cs", "source_location": "L277", "weight": 1.0}, {"source": "controllers_adminuserscontroller_adminuserscontroller_toggleuseractive", "target": "controllers_adminuserscontroller_adminuserscontroller_logactivityasync", "relation": "calls", "context": "call", "confidence": "EXTRACTED", "source_file": "C:\\Projects\\Arza\\ECommerce.API\\Controllers\\AdminUsersController.cs", "source_location": "L287", "weight": 1.0}], "raw_calls": [{"caller_nid": "controllers_adminuserscontroller_adminuserscontroller_getcurrentuserid", "callee": "FindFirstValue", "is_member_call": true, "source_file": "C:\\Projects\\Arza\\ECommerce.API\\Controllers\\AdminUsersController.cs", "source_location": "L29"}, {"caller_nid": "controllers_adminuserscontroller_adminuserscontroller_getclientip", "callee": "ToString", "is_member_call": true, "source_file": "C:\\Projects\\Arza\\ECommerce.API\\Controllers\\AdminUsersController.cs", "source_location": "L30"}, {"caller_nid": "controllers_adminuserscontroller_adminuserscontroller_logactivityasync", "callee": "Add", "is_member_call": true, "source_file": "C:\\Projects\\Arza\\ECommerce.API\\Controllers\\AdminUsersController.cs", "source_location": "L43"}, {"caller_nid": "controllers_adminuserscontroller_adminuserscontroller_logactivityasync", "callee": "SaveChangesAsync", "is_member_call": true, "source_file": "C:\\Projects\\Arza\\ECommerce.API\\Controllers\\AdminUsersController.cs", "source_location": "L44"}, {"caller_nid": "controllers_adminuserscontroller_adminuserscontroller_getadminusers", "callee": "ToListAsync", "is_member_call": true, "source_file": "C:\\Projects\\Arza\\ECommerce.API\\Controllers\\AdminUsersController.cs", "source_location": "L50"}, {"caller_nid": "controllers_adminuserscontroller_adminuserscontroller_getadminusers", "callee": "ThenBy", "is_member_call": true, "source_file": "C:\\Projects\\Arza\\ECommerce.API\\Controllers\\AdminUsersController.cs", "source_location": "L50"}, {"caller_nid": "controllers_adminuserscontroller_adminuserscontroller_getadminusers", "callee": "OrderByDescending", "is_member_call": true, "source_file": "C:\\Projects\\Arza\\ECommerce.API\\Controllers\\AdminUsersController.cs", "source_location": "L50"}, {"caller_nid": "controllers_adminuserscontroller_adminuserscontroller_getadminusers", "callee": "Select", "is_member_call": true, "source_file": "C:\\Projects\\Arza\\ECommerce.API\\Controllers\\AdminUsersController.cs", "source_location": "L50"}, {"caller_nid": "controllers_adminuserscontroller_adminuserscontroller_getadminusers", "callee": "Where", "is_member_call": true, "source_file": "C:\\Projects\\Arza\\ECommerce.API\\Controllers\\AdminUsersController.cs", "source_location": "L50"}, {"caller_nid": "controllers_adminuserscontroller_adminuserscontroller_getadminusers", "callee": "Deserialize<List<string>>", "is_member_call": true, "source_file": "C:\\Projects\\Arza\\ECommerce.API\\Controllers\\AdminUsersController.cs", "source_location": "L63"}, {"caller_nid": "controllers_adminuserscontroller_adminuserscontroller_getadminusers", "callee": "Ok", "is_member_call": false, "source_file": "C:\\Projects\\Arza\\ECommerce.API\\Controllers\\AdminUsersController.cs", "source_location": "L70"}, {"caller_nid": "controllers_adminuserscontroller_adminuserscontroller_createadminuser", "callee": "IsNullOrWhiteSpace", "is_member_call": true, "source_file": "C:\\Projects\\Arza\\ECommerce.API\\Controllers\\AdminUsersController.cs", "source_location": "L77"}, {"caller_nid": "controllers_adminuserscontroller_adminuserscontroller_createadminuser", "callee": "IsNullOrWhiteSpace", "is_member_call": true, "source_file": "C:\\Projects\\Arza\\ECommerce.API\\Controllers\\AdminUsersController.cs", "source_location": "L77"}, {"caller_nid": "controllers_adminuserscontroller_adminuserscontroller_createadminuser", "callee": "BadRequest", "is_member_call": false, "source_file": "C:\\Projects\\Arza\\ECommerce.API\\Controllers\\AdminUsersController.cs", "source_location": "L78"}, {"caller_nid": "controllers_adminuserscontroller_adminuserscontroller_createadminuser", "callee": "BadRequest", "is_member_call": false, "source_file": "C:\\Projects\\Arza\\ECommerce.API\\Controllers\\AdminUsersController.cs", "source_location": "L81"}, {"caller_nid": "controllers_adminuserscontroller_adminuserscontroller_createadminuser", "callee": "FindByNameAsync", "is_member_call": true, "source_file": "C:\\Projects\\Arza\\ECommerce.API\\Controllers\\AdminUsersController.cs", "source_location": "L83"}, {"caller_nid": "controllers_adminuserscontroller_adminuserscontroller_createadminuser", "callee": "BadRequest", "is_member_call": false, "source_file": "C:\\Projects\\Arza\\ECommerce.API\\Controllers\\AdminUsersController.cs", "source_location": "L85"}, {"caller_nid": "controllers_adminuserscontroller_adminuserscontroller_createadminuser", "callee": "IsNullOrWhiteSpace", "is_member_call": true, "source_file": "C:\\Projects\\Arza\\ECommerce.API\\Controllers\\AdminUsersController.cs", "source_location": "L87"}, {"caller_nid": "controllers_adminuserscontroller_adminuserscontroller_createadminuser", "callee": "FindByEmailAsync", "is_member_call": true, "source_file": "C:\\Projects\\Arza\\ECommerce.API\\Controllers\\AdminUsersController.cs", "source_location": "L89"}, {"caller_nid": "controllers_adminuserscontroller_adminuserscontroller_createadminuser", "callee": "BadRequest", "is_member_call": false, "source_file": "C:\\Projects\\Arza\\ECommerce.API\\Controllers\\AdminUsersController.cs", "source_location": "L91"}, {"caller_nid": "controllers_adminuserscontroller_adminuserscontroller_createadminuser", "callee": "IsNullOrWhiteSpace", "is_member_call": true, "source_file": "C:\\Projects\\Arza\\ECommerce.API\\Controllers\\AdminUsersController.cs", "source_location": "L94"}, {"caller_nid": "controllers_adminuserscontroller_adminuserscontroller_createadminuser", "callee": "BadRequest", "is_member_call": false, "source_file": "C:\\Projects\\Arza\\ECommerce.API\\Controllers\\AdminUsersController.cs", "source_location": "L96"}, {"caller_nid": "controllers_adminuserscontroller_adminuserscontroller_createadminuser", "callee": "Encrypt", "is_member_call": true, "source_file": "C:\\Projects\\Arza\\ECommerce.API\\Controllers\\AdminUsersController.cs", "source_location": "L98"}, {"caller_nid": "controllers_adminuserscontroller_adminuserscontroller_createadminuser", "callee": "IsNullOrWhiteSpace", "is_member_call": true, "source_file": "C:\\Projects\\Arza\\ECommerce.API\\Controllers\\AdminUsersController.cs", "source_location": "L109"}, {"caller_nid": "controllers_adminuserscontroller_adminuserscontroller_createadminuser", "callee": "CreateAsync", "is_member_call": true, "source_file": "C:\\Projects\\Arza\\ECommerce.API\\Controllers\\AdminUsersController.cs", "source_location": "L114"}, {"caller_nid": "controllers_adminuserscontroller_adminuserscontroller_createadminuser", "callee": "BadRequest", "is_member_call": false, "source_file": "C:\\Projects\\Arza\\ECommerce.API\\Controllers\\AdminUsersController.cs", "source_location": "L116"}, {"caller_nid": "controllers_adminuserscontroller_adminuserscontroller_createadminuser", "callee": "Join", "is_member_call": true, "source_file": "C:\\Projects\\Arza\\ECommerce.API\\Controllers\\AdminUsersController.cs", "source_location": "L116"}, {"caller_nid": "controllers_adminuserscontroller_adminuserscontroller_createadminuser", "callee": "Select", "is_member_call": true, "source_file": "C:\\Projects\\Arza\\ECommerce.API\\Controllers\\AdminUsersController.cs", "source_location": "L116"}, {"caller_nid": "controllers_adminuserscontroller_adminuserscontroller_createadminuser", "callee": "AddToRoleAsync", "is_member_call": true, "source_file": "C:\\Projects\\Arza\\ECommerce.API\\Controllers\\AdminUsersController.cs", "source_location": "L118"}, {"caller_nid": "controllers_adminuserscontroller_adminuserscontroller_createadminuser", "callee": "Ok", "is_member_call": false, "source_file": "C:\\Projects\\Arza\\ECommerce.API\\Controllers\\AdminUsersController.cs", "source_location": "L121"}, {"caller_nid": "controllers_adminuserscontroller_adminuserscontroller_updateadminuser", "callee": "FindByIdAsync", "is_member_call": true, "source_file": "C:\\Projects\\Arza\\ECommerce.API\\Controllers\\AdminUsersController.cs", "source_location": "L143"}, {"caller_nid": "controllers_adminuserscontroller_adminuserscontroller_updateadminuser", "callee": "NotFound", "is_member_call": false, "source_file": "C:\\Projects\\Arza\\ECommerce.API\\Controllers\\AdminUsersController.cs", "source_location": "L144"}, {"caller_nid": "controllers_adminuserscontroller_adminuserscontroller_updateadminuser", "callee": "IsNullOrWhiteSpace", "is_member_call": true, "source_file": "C:\\Projects\\Arza\\ECommerce.API\\Controllers\\AdminUsersController.cs", "source_location": "L148"}, {"caller_nid": "controllers_adminuserscontroller_adminuserscontroller_updateadminuser", "callee": "FindByNameAsync", "is_member_call": true, "source_file": "C:\\Projects\\Arza\\ECommerce.API\\Controllers\\AdminUsersController.cs", "source_location": "L150"}, {"caller_nid": "controllers_adminuserscontroller_adminuserscontroller_updateadminuser", "callee": "BadRequest", "is_member_call": false, "source_file": "C:\\Projects\\Arza\\ECommerce.API\\Controllers\\AdminUsersController.cs", "source_location": "L152"}, {"caller_nid": "controllers_adminuserscontroller_adminuserscontroller_updateadminuser", "callee": "Add", "is_member_call": true, "source_file": "C:\\Projects\\Arza\\ECommerce.API\\Controllers\\AdminUsersController.cs", "source_location": "L153"}, {"caller_nid": "controllers_adminuserscontroller_adminuserscontroller_updateadminuser", "callee": "IsNullOrWhiteSpace", "is_member_call": true, "source_file": "C:\\Projects\\Arza\\ECommerce.API\\Controllers\\AdminUsersController.cs", "source_location": "L157"}, {"caller_nid": "controllers_adminuserscontroller_adminuserscontroller_updateadminuser", "callee": "FindByEmailAsync", "is_member_call": true, "source_file": "C:\\Projects\\Arza\\ECommerce.API\\Controllers\\AdminUsersController.cs", "source_location": "L159"}, {"caller_nid": "controllers_adminuserscontroller_adminuserscontroller_updateadminuser", "callee": "BadRequest", "is_member_call": false, "source_file": "C:\\Projects\\Arza\\ECommerce.API\\Controllers\\AdminUsersController.cs", "source_location": "L161"}, {"caller_nid": "controllers_adminuserscontroller_adminuserscontroller_updateadminuser", "callee": "Add", "is_member_call": true, "source_file": "C:\\Projects\\Arza\\ECommerce.API\\Controllers\\AdminUsersController.cs", "source_location": "L162"}, {"caller_nid": "controllers_adminuserscontroller_adminuserscontroller_updateadminuser", "callee": "IsNullOrWhiteSpace", "is_member_call": true, "source_file": "C:\\Projects\\Arza\\ECommerce.API\\Controllers\\AdminUsersController.cs", "source_location": "L166"}, {"caller_nid": "controllers_adminuserscontroller_adminuserscontroller_updateadminuser", "callee": "BadRequest", "is_member_call": false, "source_file": "C:\\Projects\\Arza\\ECommerce.API\\Controllers\\AdminUsersController.cs", "source_location": "L169"}, {"caller_nid": "controllers_adminuserscontroller_adminuserscontroller_updateadminuser", "callee": "GetRolesAsync", "is_member_call": true, "source_file": "C:\\Projects\\Arza\\ECommerce.API\\Controllers\\AdminUsersController.cs", "source_location": "L171"}, {"caller_nid": "controllers_adminuserscontroller_adminuserscontroller_updateadminuser", "callee": "RemoveFromRolesAsync", "is_member_call": true, "source_file": "C:\\Projects\\Arza\\ECommerce.API\\Controllers\\AdminUsersController.cs", "source_location": "L172"}, {"caller_nid": "controllers_adminuserscontroller_adminuserscontroller_updateadminuser", "callee": "AddToRoleAsync", "is_member_call": true, "source_file": "C:\\Projects\\Arza\\ECommerce.API\\Controllers\\AdminUsersController.cs", "source_location": "L173"}, {"caller_nid": "controllers_adminuserscontroller_adminuserscontroller_updateadminuser", "callee": "Add", "is_member_call": true, "source_file": "C:\\Projects\\Arza\\ECommerce.API\\Controllers\\AdminUsersController.cs", "source_location": "L174"}, {"caller_nid": "controllers_adminuserscontroller_adminuserscontroller_updateadminuser", "callee": "Add", "is_member_call": true, "source_file": "C:\\Projects\\Arza\\ECommerce.API\\Controllers\\AdminUsersController.cs", "source_location": "L180"}, {"caller_nid": "controllers_adminuserscontroller_adminuserscontroller_updateadminuser", "callee": "Add", "is_member_call": true, "source_file": "C:\\Projects\\Arza\\ECommerce.API\\Controllers\\AdminUsersController.cs", "source_location": "L193"}, {"caller_nid": "controllers_adminuserscontroller_adminuserscontroller_updateadminuser", "callee": "UpdateAsync", "is_member_call": true, "source_file": "C:\\Projects\\Arza\\ECommerce.API\\Controllers\\AdminUsersController.cs", "source_location": "L202"}, {"caller_nid": "controllers_adminuserscontroller_adminuserscontroller_updateadminuser", "callee": "BadRequest", "is_member_call": false, "source_file": "C:\\Projects\\Arza\\ECommerce.API\\Controllers\\AdminUsersController.cs", "source_location": "L204"}, {"caller_nid": "controllers_adminuserscontroller_adminuserscontroller_updateadminuser", "callee": "Join", "is_member_call": true, "source_file": "C:\\Projects\\Arza\\ECommerce.API\\Controllers\\AdminUsersController.cs", "source_location": "L204"}, {"caller_nid": "controllers_adminuserscontroller_adminuserscontroller_updateadminuser", "callee": "Select", "is_member_call": true, "source_file": "C:\\Projects\\Arza\\ECommerce.API\\Controllers\\AdminUsersController.cs", "source_location": "L204"}, {"caller_nid": "controllers_adminuserscontroller_adminuserscontroller_updateadminuser", "callee": "IsNullOrWhiteSpace", "is_member_call": true, "source_file": "C:\\Projects\\Arza\\ECommerce.API\\Controllers\\AdminUsersController.cs", "source_location": "L206"}, {"caller_nid": "controllers_adminuserscontroller_adminuserscontroller_updateadminuser", "callee": "BadRequest", "is_member_call": false, "source_file": "C:\\Projects\\Arza\\ECommerce.API\\Controllers\\AdminUsersController.cs", "source_location": "L209"}, {"caller_nid": "controllers_adminuserscontroller_adminuserscontroller_updateadminuser", "callee": "GeneratePasswordResetTokenAsync", "is_member_call": true, "source_file": "C:\\Projects\\Arza\\ECommerce.API\\Controllers\\AdminUsersController.cs", "source_location": "L211"}, {"caller_nid": "controllers_adminuserscontroller_adminuserscontroller_updateadminuser", "callee": "ResetPasswordAsync", "is_member_call": true, "source_file": "C:\\Projects\\Arza\\ECommerce.API\\Controllers\\AdminUsersController.cs", "source_location": "L212"}, {"caller_nid": "controllers_adminuserscontroller_adminuserscontroller_updateadminuser", "callee": "BadRequest", "is_member_call": false, "source_file": "C:\\Projects\\Arza\\ECommerce.API\\Controllers\\AdminUsersController.cs", "source_location": "L214"}, {"caller_nid": "controllers_adminuserscontroller_adminuserscontroller_updateadminuser", "callee": "Join", "is_member_call": true, "source_file": "C:\\Projects\\Arza\\ECommerce.API\\Controllers\\AdminUsersController.cs", "source_location": "L214"}, {"caller_nid": "controllers_adminuserscontroller_adminuserscontroller_updateadminuser", "callee": "Select", "is_member_call": true, "source_file": "C:\\Projects\\Arza\\ECommerce.API\\Controllers\\AdminUsersController.cs", "source_location": "L214"}, {"caller_nid": "controllers_adminuserscontroller_adminuserscontroller_updateadminuser", "callee": "Encrypt", "is_member_call": true, "source_file": "C:\\Projects\\Arza\\ECommerce.API\\Controllers\\AdminUsersController.cs", "source_location": "L216"}, {"caller_nid": "controllers_adminuserscontroller_adminuserscontroller_updateadminuser", "callee": "UpdateAsync", "is_member_call": true, "source_file": "C:\\Projects\\Arza\\ECommerce.API\\Controllers\\AdminUsersController.cs", "source_location": "L217"}, {"caller_nid": "controllers_adminuserscontroller_adminuserscontroller_updateadminuser", "callee": "Add", "is_member_call": true, "source_file": "C:\\Projects\\Arza\\ECommerce.API\\Controllers\\AdminUsersController.cs", "source_location": "L218"}, {"caller_nid": "controllers_adminuserscontroller_adminuserscontroller_updateadminuser", "callee": "Join", "is_member_call": true, "source_file": "C:\\Projects\\Arza\\ECommerce.API\\Controllers\\AdminUsersController.cs", "source_location": "L222"}, {"caller_nid": "controllers_adminuserscontroller_adminuserscontroller_updateadminuser", "callee": "Ok", "is_member_call": false, "source_file": "C:\\Projects\\Arza\\ECommerce.API\\Controllers\\AdminUsersController.cs", "source_location": "L224"}, {"caller_nid": "controllers_adminuserscontroller_adminuserscontroller_resetadminuserpassword", "callee": "IsNullOrWhiteSpace", "is_member_call": true, "source_file": "C:\\Projects\\Arza\\ECommerce.API\\Controllers\\AdminUsersController.cs", "source_location": "L231"}, {"caller_nid": "controllers_adminuserscontroller_adminuserscontroller_resetadminuserpassword", "callee": "BadRequest", "is_member_call": false, "source_file": "C:\\Projects\\Arza\\ECommerce.API\\Controllers\\AdminUsersController.cs", "source_location": "L232"}, {"caller_nid": "controllers_adminuserscontroller_adminuserscontroller_resetadminuserpassword", "callee": "BadRequest", "is_member_call": false, "source_file": "C:\\Projects\\Arza\\ECommerce.API\\Controllers\\AdminUsersController.cs", "source_location": "L235"}, {"caller_nid": "controllers_adminuserscontroller_adminuserscontroller_resetadminuserpassword", "callee": "FindByIdAsync", "is_member_call": true, "source_file": "C:\\Projects\\Arza\\ECommerce.API\\Controllers\\AdminUsersController.cs", "source_location": "L237"}, {"caller_nid": "controllers_adminuserscontroller_adminuserscontroller_resetadminuserpassword", "callee": "NotFound", "is_member_call": false, "source_file": "C:\\Projects\\Arza\\ECommerce.API\\Controllers\\AdminUsersController.cs", "source_location": "L238"}, {"caller_nid": "controllers_adminuserscontroller_adminuserscontroller_resetadminuserpassword", "callee": "GeneratePasswordResetTokenAsync", "is_member_call": true, "source_file": "C:\\Projects\\Arza\\ECommerce.API\\Controllers\\AdminUsersController.cs", "source_location": "L240"}, {"caller_nid": "controllers_adminuserscontroller_adminuserscontroller_resetadminuserpassword", "callee": "ResetPasswordAsync", "is_member_call": true, "source_file": "C:\\Projects\\Arza\\ECommerce.API\\Controllers\\AdminUsersController.cs", "source_location": "L241"}, {"caller_nid": "controllers_adminuserscontroller_adminuserscontroller_resetadminuserpassword", "callee": "BadRequest", "is_member_call": false, "source_file": "C:\\Projects\\Arza\\ECommerce.API\\Controllers\\AdminUsersController.cs", "source_location": "L243"}, {"caller_nid": "controllers_adminuserscontroller_adminuserscontroller_resetadminuserpassword", "callee": "Join", "is_member_call": true, "source_file": "C:\\Projects\\Arza\\ECommerce.API\\Controllers\\AdminUsersController.cs", "source_location": "L243"}, {"caller_nid": "controllers_adminuserscontroller_adminuserscontroller_resetadminuserpassword", "callee": "Select", "is_member_call": true, "source_file": "C:\\Projects\\Arza\\ECommerce.API\\Controllers\\AdminUsersController.cs", "source_location": "L243"}, {"caller_nid": "controllers_adminuserscontroller_adminuserscontroller_resetadminuserpassword", "callee": "Encrypt", "is_member_call": true, "source_file": "C:\\Projects\\Arza\\ECommerce.API\\Controllers\\AdminUsersController.cs", "source_location": "L245"}, {"caller_nid": "controllers_adminuserscontroller_adminuserscontroller_resetadminuserpassword", "callee": "UpdateAsync", "is_member_call": true, "source_file": "C:\\Projects\\Arza\\ECommerce.API\\Controllers\\AdminUsersController.cs", "source_location": "L246"}, {"caller_nid": "controllers_adminuserscontroller_adminuserscontroller_resetadminuserpassword", "callee": "Ok", "is_member_call": false, "source_file": "C:\\Projects\\Arza\\ECommerce.API\\Controllers\\AdminUsersController.cs", "source_location": "L250"}, {"caller_nid": "controllers_adminuserscontroller_adminuserscontroller_getuserpassword", "callee": "FindByIdAsync", "is_member_call": true, "source_file": "C:\\Projects\\Arza\\ECommerce.API\\Controllers\\AdminUsersController.cs", "source_location": "L257"}, {"caller_nid": "controllers_adminuserscontroller_adminuserscontroller_getuserpassword", "callee": "NotFound", "is_member_call": false, "source_file": "C:\\Projects\\Arza\\ECommerce.API\\Controllers\\AdminUsersController.cs", "source_location": "L258"}, {"caller_nid": "controllers_adminuserscontroller_adminuserscontroller_getuserpassword", "callee": "IsNullOrEmpty", "is_member_call": true, "source_file": "C:\\Projects\\Arza\\ECommerce.API\\Controllers\\AdminUsersController.cs", "source_location": "L260"}, {"caller_nid": "controllers_adminuserscontroller_adminuserscontroller_getuserpassword", "callee": "Ok", "is_member_call": false, "source_file": "C:\\Projects\\Arza\\ECommerce.API\\Controllers\\AdminUsersController.cs", "source_location": "L261"}, {"caller_nid": "controllers_adminuserscontroller_adminuserscontroller_getuserpassword", "callee": "Decrypt", "is_member_call": true, "source_file": "C:\\Projects\\Arza\\ECommerce.API\\Controllers\\AdminUsersController.cs", "source_location": "L263"}, {"caller_nid": "controllers_adminuserscontroller_adminuserscontroller_getuserpassword", "callee": "Ok", "is_member_call": false, "source_file": "C:\\Projects\\Arza\\ECommerce.API\\Controllers\\AdminUsersController.cs", "source_location": "L267"}, {"caller_nid": "controllers_adminuserscontroller_adminuserscontroller_toggleuseractive", "callee": "FindByIdAsync", "is_member_call": true, "source_file": "C:\\Projects\\Arza\\ECommerce.API\\Controllers\\AdminUsersController.cs", "source_location": "L274"}, {"caller_nid": "controllers_adminuserscontroller_adminuserscontroller_toggleuseractive", "callee": "NotFound", "is_member_call": false, "source_file": "C:\\Projects\\Arza\\ECommerce.API\\Controllers\\AdminUsersController.cs", "source_location": "L275"}, {"caller_nid": "controllers_adminuserscontroller_adminuserscontroller_toggleuseractive", "callee": "BadRequest", "is_member_call": false, "source_file": "C:\\Projects\\Arza\\ECommerce.API\\Controllers\\AdminUsersController.cs", "source_location": "L279"}, {"caller_nid": "controllers_adminuserscontroller_adminuserscontroller_toggleuseractive", "callee": "BadRequest", "is_member_call": false, "source_file": "C:\\Projects\\Arza\\ECommerce.API\\Controllers\\AdminUsersController.cs", "source_location": "L282"}, {"caller_nid": "controllers_adminuserscontroller_adminuserscontroller_toggleuseractive", "callee": "UpdateAsync", "is_member_call": true, "source_file": "C:\\Projects\\Arza\\ECommerce.API\\Controllers\\AdminUsersController.cs", "source_location": "L285"}, {"caller_nid": "controllers_adminuserscontroller_adminuserscontroller_toggleuseractive", "callee": "Ok", "is_member_call": false, "source_file": "C:\\Projects\\Arza\\ECommerce.API\\Controllers\\AdminUsersController.cs", "source_location": "L289"}, {"caller_nid": "controllers_adminuserscontroller_adminuserscontroller_getactivitylog", "callee": "FindByIdAsync", "is_member_call": true, "source_file": "C:\\Projects\\Arza\\ECommerce.API\\Controllers\\AdminUsersController.cs", "source_location": "L296"}, {"caller_nid": "controllers_adminuserscontroller_adminuserscontroller_getactivitylog", "callee": "NotFound", "is_member_call": false, "source_file": "C:\\Projects\\Arza\\ECommerce.API\\Controllers\\AdminUsersController.cs", "source_location": "L297"}, {"caller_nid": "controllers_adminuserscontroller_adminuserscontroller_getactivitylog", "callee": "ToListAsync", "is_member_call": true, "source_file": "C:\\Projects\\Arza\\ECommerce.API\\Controllers\\AdminUsersController.cs", "source_location": "L299"}, {"caller_nid": "controllers_adminuserscontroller_adminuserscontroller_getactivitylog", "callee": "Select", "is_member_call": true, "source_file": "C:\\Projects\\Arza\\ECommerce.API\\Controllers\\AdminUsersController.cs", "source_location": "L299"}, {"caller_nid": "controllers_adminuserscontroller_adminuserscontroller_getactivitylog", "callee": "Take", "is_member_call": true, "source_file": "C:\\Projects\\Arza\\ECommerce.API\\Controllers\\AdminUsersController.cs", "source_location": "L299"}, {"caller_nid": "controllers_adminuserscontroller_adminuserscontroller_getactivitylog", "callee": "OrderByDescending", "is_member_call": true, "source_file": "C:\\Projects\\Arza\\ECommerce.API\\Controllers\\AdminUsersController.cs", "source_location": "L299"}, {"caller_nid": "controllers_adminuserscontroller_adminuserscontroller_getactivitylog", "callee": "Where", "is_member_call": true, "source_file": "C:\\Projects\\Arza\\ECommerce.API\\Controllers\\AdminUsersController.cs", "source_location": "L299"}, {"caller_nid": "controllers_adminuserscontroller_adminuserscontroller_getactivitylog", "callee": "Ok", "is_member_call": false, "source_file": "C:\\Projects\\Arza\\ECommerce.API\\Controllers\\AdminUsersController.cs", "source_location": "L314"}]}